pandaforce/__init__.py
pandaforce/pandaforce.py
pandaforce-1.1.0.dist-info/LICENSE.txt
pandaforce-1.1.0.dist-info/METADATA
pandaforce-1.1.0.dist-info/WHEEL
pandaforce-1.1.0.dist-info/top_level.txt
pandaforce-1.1.0.dist-info/RECORD
