Metadata-Version: 2.1
Name: pandaforce
Version: 1.1.0
Summary: A pandas and simple-salesforce based utility package
Home-page: https://github.com/Jwok90/pandaforce
Author: Jamil Vallis-Walker
Author-email: 
License: UNKNOWN
Platform: UNKNOWN
Classifier: Programming Language :: Python :: 3
Classifier: License :: OSI Approved :: MIT License
Classifier: Operating System :: OS Independent
